[
   {
    "type": "heading",
    "title": "Welcome to the Prompt Library!",
    "content": null,
    "image_url": null
  },
  {
    "type": "text",
    "content": "This lesson will test your knowledge and understanding of the key concepts and techniques covered in our previous lessons.\n\nEach question is designed to help you reflect on what you've learned and apply it in practical scenarios. Good luck!"
  },
  {
    "type": "image",
    "image_url": "./lesson no 15_files/68ae3201-35bd-4fbc-907c-b263e30a3600.webp",
    "alt_text": ""
  }
]
